rtl/ALU.v
module ALU (
    input [31:0] in1, in2,  // Input operands
    input [3:0] alu_control, // ALU control lines
    output reg [31:0] alu_result, // Result of ALU operation
    output reg zero_flag // Flag indicating if result is zero
);
    always @(*)
    begin
        // Operating based on control input
        case(alu_control)
            4'b0000: alu_result = in1 + in2; // Addition
            4'b0001: alu_result = in1 - in2; // Subtraction
            4'b0010: alu_result = in1 || in2; // Logical OR
            4'b0011: alu_result = in1 && in2; // Logical AND
            4'b0100: alu_result = in1 ^ in2; // XOR
            4'b0101: begin 
                if (in1 < in2) // Set on less than
                    alu_result = 1; 
                else
                    alu_result = 0;
            end
        endcase

        // Setting Zero_flag if ALU_result is zero
        if (alu_result == 0)
            zero_flag = 1'b1;
        else
            zero_flag = 1'b0;
    end
endmodule

rtl/REG_FILE.v
module REG_FILE(
    input [4:0] read_reg_num1,
    input [4:0] read_reg_num2,
    input [4:0] write_reg,
    input [31:0] write_data,
    output [31:0] read_data1,
    output [31:0] read_data2,
    input regwrite,
    input clock,
    input reset
);

    reg [31:0] reg_memory [31:0]; // 32 memory locations each 32 bits wide

    // When reset is asserted, initialize registers with some values
  always @(posedge clock)
    begin
      if (!reset) begin
            for (int i = 0; i < 32; i++)
                reg_memory[i] = i;
end
//          else begin
//             // If reset is de-asserted, initialize to 1
//             for (int i = 0; i < 32; i++)
//                 reg_memory[i] = 0;
//         end
    end

    // The register file will always output the values corresponding to read register numbers 
    // It is independent of any other signal
    assign read_data1 = reg_memory[read_reg_num1];
    assign read_data2 = reg_memory[read_reg_num2];

    // If clock edge is positive and regwrite is 1, we write data to specified register
    always @(posedge clock)
    begin
        if (regwrite) begin
            reg_memory[write_reg] <= write_data;
        end     
    end

endmodule

rtl/DATAPATH.v
`include "REG_FILE.v"
`include "ALU.v"

module DATAPATH(
    input [4:0] read_reg_num1,
    input [4:0] read_reg_num2,
    input [4:0] write_reg,
    input [3:0] alu_control,
    input reg regwrite,
    input clock,
    input reset,
    output zero_flag
);

    // Declaring internal wires that carry data
    wire [31:0] read_data1;
    wire [31:0] read_data2;
    wire [31:0] write_data;

    // Instantiating the register file and ALU
    REG_FILE reg_file_module(read_reg_num1, read_reg_num2, write_reg, write_data, read_data1, read_data2, regwrite, clock, reset);
    ALU alu_module(read_data1, read_data2, alu_control, write_data, zero_flag);
	 
endmodule

rtl/CONTROL.v
module CONTROL(
    input [6:0] funct7,
    input [2:0] funct3,
    input [6:0] opcode,
    output reg [3:0] alu_control,
    output reg regwrite_control
);
    always @(funct3 or funct7 or opcode)
    begin
        if (opcode == 7'b0110011) begin // R-type instructions

            regwrite_control = 1;

            case (funct3)
                0: begin
                    if(funct7 == 0)
                    alu_control = 4'b0000; // ADD
                    else if(funct7 == 32)
                    alu_control = 4'b0001; // SUB
                    end
              
                6: alu_control = 4'b0010; // logical OR
                7: alu_control = 4'b0011; // logicalAND
                4: alu_control = 4'b0100; // XOR
				2: alu_control = 4'b0101; // SLT
                
             
            endcase

      end

    end

endmodule

rtl/INST_MEM.v
/* 
   Instruction memory takes in two inputs: A 32-bit Program counter and a 1-bit reset. 
   The memory is initialized when reset is 1.
   When reset is set to 0, Based on the value of PC, corresponding 32-bit Instruction code is output.
*/

module INST_MEM(
    input [31:0] PC,
    input reset,clock,
    output [31:0] Instruction_Code
);

    reg [7:0] Memory [23:0]; // Byte addressable memory with 32 locations

    // Under normal operation (reset = 0), we assign the instr. code, based on PC
    assign Instruction_Code = {Memory[PC+3], Memory[PC+2], Memory[PC+1], Memory[PC]};

    // Initializing memory when reset is one
  always @(posedge clock)
    begin
      if (reset == 0)
        begin
            // Setting 32-bit instruction: add t1, s0, s1 => 0x00940333 
            Memory[3] = 8'h00;
            Memory[2] = 8'h94;
            Memory[1] = 8'h03;
            Memory[0] = 8'h33;
            // Setting 32-bit instruction: sub t2, s3, s2 => 0x412983b3
            Memory[7] = 8'h41;
            Memory[6] = 8'h29;
            Memory[5] = 8'h83;
            Memory[4] = 8'hb3;
            // Setting 32-bit instruction: or a7, a4, a5 => 0x00f768b3
            Memory[11] = 8'h00;
            Memory[10] = 8'hf7;
            Memory[9] = 8'h68;
            Memory[8] = 8'hb3;
            // Setting 32-bit instruction: and t6, a2, a3 => 0x00d67fb3
            Memory[15] = 8'h00;
            Memory[14] = 8'hd6;
            Memory[13] = 8'h7f;
            Memory[12] = 8'hb3;
            // Setting 32-bit instruction: xor t3, s6, s7 => 0x017b4e33
            Memory[19] = 8'h01;
            Memory[18] = 8'h7b;
            Memory[17] = 8'h4e;
            Memory[16] = 8'h33;
            // Setting 32-bit instruction: slt t5, s10, s11 => 0x01bdaf33
            Memory[23] = 8'h01;
            Memory[22] = 8'hbd;
            Memory[21] = 8'haf;
            Memory[20] = 8'h33;
        end
    end

endmodule

rtl/IFU.v
`include "INST_MEM.v"

module IFU(
    input clock, 
    input reset, 
    output reg [31:0] Instruction_Code
);
    reg [31:0] PC = 32'b0; // Initialize program counter to zero
    reg [31:0] count = 0; // Initialize count variable

    INST_MEM instr_mem(PC, reset, clock, Instruction_Code); // Instantiate Instruction Memory block

    always @(posedge clock, posedge reset)
    begin
        if (reset == 1)
            PC <= 0; // Clear program counter on reset
        else if (count > 0)
            PC <= PC + 4; // Increment program counter by 4
        else
        begin
            PC <= PC; // Maintain program counter
            count <= count + 1; // Increment count
        end
    end

endmodule

rtl/PROCESSOR.v
`include "CONTROL.v"
`include "DATAPATH.v"
`include "IFU.v"

module PROCESSOR( 
    input clock, 
    input reset,
    output zero
);

    wire [31:0] instruction_code;
    wire [3:0] alu_control;
    wire regwrite;

    IFU IFU_module(clock, reset, instruction_code);
	
    CONTROL control_module(instruction_code[31:25], instruction_code[14:12],instruction_code[6:0], alu_control, regwrite);
	
    DATAPATH datapath_module(instruction_code[19:15], instruction_code[24:20], instruction_code[11:7], alu_control, regwrite, clock, reset, zero);

endmodule

testbench/testbench.v
`include "PROCESSOR.v"

module stimulus ();

    reg clock;
    reg reset;
    wire zero;

    // Instantiating the processor
    PROCESSOR test_processor(clock, reset, zero);

    initial begin
        $dumpfile("output_wave.vcd");
        $dumpvars(0, stimulus);
    end

    initial begin
        reset = 1;
        #50 reset = 0;
    end

    initial begin
        clock = 0;
        forever #20 clock = ~clock;
    end

    initial
    #500 $finish;

endmodule

rtl/output_wave.vcd
$date
	Thu Mar 21 08:43:22 2024
$end
$version
	QuestaSim Version 2021.3
$end
$timescale
	1ns
$end

$scope module stimulus $end
$var wire 1 ! zero $end
$var reg 1 " clock $end
$var reg 1 # reset $end

$scope module test_processor $end
$var wire 4 $ alu_control [3:0] $end
$var wire 1 % clock $end
$var wire 32 & instruction_code [31:0] $end
$var wire 1 ' regwrite $end
$var wire 1 ( reset $end
$var wire 1 ! zero $end

$scope module IFU_module $end
$var wire 32 & Instruction_Code [31:0] $end
$var wire 1 % clock $end
$var wire 1 ( reset $end
$var reg 32 ) PC [31:0] $end
$var reg 32 * count [31:0] $end

$scope module instr_mem $end
$var wire 32 & Instruction_Code [31:0] $end
$var wire 32 + PC [31:0] $end
$var wire 1 % clock $end
$var wire 1 ( reset $end
$upscope $end
$upscope $end

$scope module control_module $end
$var wire 3 , funct3 [2:0] $end
$var wire 7 - funct7 [6:0] $end
$var wire 7 . opcode [6:0] $end
$var reg 4 / alu_control [3:0] $end
$var reg 1 0 regwrite_control $end
$upscope $end

$scope module datapath_module $end
$var wire 4 $ alu_control [3:0] $end
$var wire 1 % clock $end
$var wire 32 1 read_data1 [31:0] $end
$var wire 32 2 read_data2 [31:0] $end
$var wire 5 3 read_reg_num1 [4:0] $end
$var wire 5 4 read_reg_num2 [4:0] $end
$var wire 1 ' regwrite $end
$var wire 1 ( reset $end
$var wire 32 5 write_data [31:0] $end
$var wire 5 6 write_reg [4:0] $end
$var wire 1 ! zero_flag $end

$scope module alu_module $end
$var wire 4 $ alu_control [3:0] $end
$var wire 32 1 in1 [31:0] $end
$var wire 32 2 in2 [31:0] $end
$var reg 32 7 alu_result [31:0] $end
$var reg 1 8 zero_flag $end
$upscope $end

$scope module reg_file_module $end
$var wire 1 % clock $end
$var wire 32 1 read_data1 [31:0] $end
$var wire 32 2 read_data2 [31:0] $end
$var wire 5 3 read_reg_num1 [4:0] $end
$var wire 5 4 read_reg_num2 [4:0] $end
$var wire 1 ' regwrite $end
$var wire 1 ( reset $end
$var wire 32 5 write_data [31:0] $end
$var wire 5 6 write_reg [4:0] $end
$upscope $end
$upscope $end
$upscope $end
$upscope $end
$enddefinitions $end
#0
$dumpvars
x!
0%
1(
0"
1#
bx $
bx &
x'
b0 +
b0 )
b0 *
bx ,
bx -
bx .
bx /
x0
bx 1
bx 2
bx 3
bx 4
bx 5
bx 6
bx 7
x8
$end
#20
1"
1%
#40
0"
0%
#50
0#
0(
#60
1"
1%
b100101000000001100110011 &
b0 ,
b0 -
b110011 .
b1000 3
b1001 4
b110 6
b1000 1
b1001 2
08
10
b0 /
1'
0!
b0 $
b10001 7
b10001 5
b1 *
#80
0"
0%
#100
1"
1%
b100 )
b100 +
b1000001001010011000001110110011 &
b100000 -
b10011 3
b10010 4
b111 6
b10011 1
b10010 2
b100101 7
b1 /
b100101 5
b1 $
b1 7
b1 5
#120
0"
0%
#140
1"
1%
b1000 )
b1000 +
b111101110110100010110011 &
b110 ,
b0 -
b1110 3
b1111 4
b10001 6
b1110 1
b1111 2
b11111111111111111111111111111111 7
b10 /
b11111111111111111111111111111111 5
b10 $
b1 7
b1 5
#160
0"
0%
#180
1"
1%
b1100 )
b1100 +
b110101100111111110110011 &
b111 ,
b1100 3
b1101 4
b11111 6
b1100 1
b1101 2
b11 /
b11 $
#200
0"
0%
#220
1"
1%
b10000 )
b10000 +
b1011110110100111000110011 &
b100 ,
b10110 3
b10111 4
b11100 6
b10110 1
b10111 2
b100 /
b100 $
#240
0"
0%
#260
1"
1%
b10100 )
b10100 +
b1101111011010111100110011 &
b10 ,
b11011 3
b11011 4
b11110 6
b11011 1
b11011 2
b0 7
18
b101 /
1!
b0 5
b101 $
#280
0"
0%
#300
1"
1%
b11000 )
b11000 +
bx &
bx ,
bx -
bx .
bx 3
bx 4
bx 6
bx 1
bx 2
#320
0"
0%
#340
1"
1%
b11100 )
b11100 +
#360
0"
0%
#380
1"
1%
b100000 )
b100000 +
#400
0"
0%
#420
1"
1%
b100100 )
b100100 +
#440
0"
0%
#460
1"
1%
b101000 )
b101000 +
